[
  {
    "assemblea": "Senato",
    "codice": "04160000000",
    "tipo": "colleggioUninominale",
    "tipo_riga": "CA",
    "cand_descr_riga": "ELENA TESTOR",
    "img_lista": "",
    "descr_lista": "",
    "link_cand_lista": "",
    "voti": "26.986",
    "perc": "45,38",
    "eletto": "",
    "perc_voti_liste": "",
    "cifra_el": "",
    "perc_cifra_el": "",
    "seggi": ""
  },
  {
    "assemblea": "Senato",
    "codice": "04160000000",
    "tipo": "colleggioUninominale",
    "tipo_riga": "LI",
    "cand_descr_riga": "",
    "img_lista": "25-20180304000000-11367-0.png",
    "descr_lista": "LEGA",
    "link_cand_lista": "",
    "voti": "18.112",
    "perc": "32,41",
    "eletto": "",
    "perc_voti_liste": "",
    "cifra_el": "18.112",
    "perc_cifra_el": "32,41",
    "seggi": ""
  },
  {
    "assemblea": "Senato",
    "codice": "04160000000",
    "tipo": "colleggioUninominale",
    "tipo_riga": "LI",
    "cand_descr_riga": "",
    "img_lista": "25-20180304000000-1112-0.png",
    "descr_lista": "FORZA ITALIA",
    "link_cand_lista": "",
    "voti": "5.298",
    "perc": "9,48",
    "eletto": "",
    "perc_voti_liste": "",
    "cifra_el": "5.298",
    "perc_cifra_el": "9,48",
    "seggi": ""
  },
  {
    "assemblea": "Senato",
    "codice": "04160000000",
    "tipo": "colleggioUninominale",
    "tipo_riga": "LI",
    "cand_descr_riga": "",
    "img_lista": "25-20180304000000-11434-0.png",
    "descr_lista": "FRATELLI D'ITALIA CON GIORGIA MELONI",
    "link_cand_lista": "",
    "voti": "1.762",
    "perc": "3,15",
    "eletto": "",
    "perc_voti_liste": "",
    "cifra_el": "1.762",
    "perc_cifra_el": "3,15",
    "seggi": ""
  },
  {
    "assemblea": "Senato",
    "codice": "04160000000",
    "tipo": "colleggioUninominale",
    "tipo_riga": "LI",
    "cand_descr_riga": "",
    "img_lista": "25-20180304000000-11402-0.png",
    "descr_lista": "NOI CON L'ITALIA - UDC",
    "link_cand_lista": "",
    "voti": "607",
    "perc": "1,08",
    "eletto": "",
    "perc_voti_liste": "",
    "cifra_el": "607",
    "perc_cifra_el": "1,08",
    "seggi": ""
  },
  {
    "assemblea": "Senato",
    "codice": "04160000000",
    "tipo": "colleggioUninominale",
    "tipo_riga": "XX",
    "cand_descr_riga": "",
    "img_lista": "",
    "descr_lista": "",
    "link_cand_lista": "",
    "voti": "",
    "perc": "",
    "eletto": "",
    "perc_voti_liste": "",
    "cifra_el": "",
    "perc_cifra_el": "",
    "seggi": ""
  },
  {
    "assemblea": "Senato",
    "codice": "04160000000",
    "tipo": "colleggioUninominale",
    "tipo_riga": "CA",
    "cand_descr_riga": "ELEONORA STENICO",
    "img_lista": "",
    "descr_lista": "",
    "link_cand_lista": "",
    "voti": "16.049",
    "perc": "26,99",
    "eletto": "",
    "perc_voti_liste": "",
    "cifra_el": "",
    "perc_cifra_el": "",
    "seggi": ""
  },
  {
    "assemblea": "Senato",
    "codice": "04160000000",
    "tipo": "colleggioUninominale",
    "tipo_riga": "LI",
    "cand_descr_riga": "",
    "img_lista": "25-20180304000000-3456-0.png",
    "descr_lista": "PARTITO DEMOCRATICO",
    "link_cand_lista": "",
    "voti": "8.100",
    "perc": "14,49",
    "eletto": "",
    "perc_voti_liste": "",
    "cifra_el": "8.100",
    "perc_cifra_el": "14,49",
    "seggi": ""
  },
  {
    "assemblea": "Senato",
    "codice": "04160000000",
    "tipo": "colleggioUninominale",
    "tipo_riga": "LI",
    "cand_descr_riga": "",
    "img_lista": "25-20180304000000-11384-0.png",
    "descr_lista": "SVP - PATT",
    "link_cand_lista": "",
    "voti": "3.220",
    "perc": "5,76",
    "eletto": "",
    "perc_voti_liste": "",
    "cifra_el": "3.220",
    "perc_cifra_el": "5,76",
    "seggi": ""
  },
  {
    "assemblea": "Senato",
    "codice": "04160000000",
    "tipo": "colleggioUninominale",
    "tipo_riga": "LI",
    "cand_descr_riga": "",
    "img_lista": "25-20180304000000-11412-0.png",
    "descr_lista": "CIVICA POPOLARE LORENZIN",
    "link_cand_lista": "",
    "voti": "1.894",
    "perc": "3,39",
    "eletto": "",
    "perc_voti_liste": "",
    "cifra_el": "1.894",
    "perc_cifra_el": "3,39",
    "seggi": ""
  },
  {
    "assemblea": "Senato",
    "codice": "04160000000",
    "tipo": "colleggioUninominale",
    "tipo_riga": "LI",
    "cand_descr_riga": "",
    "img_lista": "25-20180304000000-11403-0.png",
    "descr_lista": "+EUROPA",
    "link_cand_lista": "",
    "voti": "1.278",
    "perc": "2,28",
    "eletto": "",
    "perc_voti_liste": "",
    "cifra_el": "1.278",
    "perc_cifra_el": "2,28",
    "seggi": ""
  },
  {
    "assemblea": "Senato",
    "codice": "04160000000",
    "tipo": "colleggioUninominale",
    "tipo_riga": "LI",
    "cand_descr_riga": "",
    "img_lista": "25-20180304000000-11373-A.png",
    "descr_lista": "ITALIA EUROPA INSIEME",
    "link_cand_lista": "",
    "voti": "382",
    "perc": "0,68",
    "eletto": "",
    "perc_voti_liste": "",
    "cifra_el": "382",
    "perc_cifra_el": "0,68",
    "seggi": ""
  },
  {
    "assemblea": "Senato",
    "codice": "04160000000",
    "tipo": "colleggioUninominale",
    "tipo_riga": "XX",
    "cand_descr_riga": "",
    "img_lista": "",
    "descr_lista": "",
    "link_cand_lista": "",
    "voti": "",
    "perc": "",
    "eletto": "",
    "perc_voti_liste": "",
    "cifra_el": "",
    "perc_cifra_el": "",
    "seggi": ""
  },
  {
    "assemblea": "Senato",
    "codice": "04160000000",
    "tipo": "colleggioUninominale",
    "tipo_riga": "CA",
    "cand_descr_riga": "GIANNI MARZI",
    "img_lista": "",
    "descr_lista": "",
    "link_cand_lista": "",
    "voti": "13.304",
    "perc": "22,37",
    "eletto": "",
    "perc_voti_liste": "",
    "cifra_el": "",
    "perc_cifra_el": "",
    "seggi": ""
  },
  {
    "assemblea": "Senato",
    "codice": "04160000000",
    "tipo": "colleggioUninominale",
    "tipo_riga": "LI",
    "cand_descr_riga": "",
    "img_lista": "25-20180304000000-11366-0.png",
    "descr_lista": "MOVIMENTO 5 STELLE",
    "link_cand_lista": "",
    "voti": "12.355",
    "perc": "22,11",
    "eletto": "",
    "perc_voti_liste": "",
    "cifra_el": "12.355",
    "perc_cifra_el": "22,11",
    "seggi": ""
  },
  {
    "assemblea": "Senato",
    "codice": "04160000000",
    "tipo": "colleggioUninominale",
    "tipo_riga": "XX",
    "cand_descr_riga": "",
    "img_lista": "",
    "descr_lista": "",
    "link_cand_lista": "",
    "voti": "",
    "perc": "",
    "eletto": "",
    "perc_voti_liste": "",
    "cifra_el": "",
    "perc_cifra_el": "",
    "seggi": ""
  },
  {
    "assemblea": "Senato",
    "codice": "04160000000",
    "tipo": "colleggioUninominale",
    "tipo_riga": "CA",
    "cand_descr_riga": "VINCENZO CALI'",
    "img_lista": "",
    "descr_lista": "",
    "link_cand_lista": "",
    "voti": "1.414",
    "perc": "2,37",
    "eletto": "",
    "perc_voti_liste": "",
    "cifra_el": "",
    "perc_cifra_el": "",
    "seggi": ""
  },
  {
    "assemblea": "Senato",
    "codice": "04160000000",
    "tipo": "colleggioUninominale",
    "tipo_riga": "LI",
    "cand_descr_riga": "",
    "img_lista": "25-20180304000000-11393-A.png",
    "descr_lista": "LIBERI E UGUALI",
    "link_cand_lista": "",
    "voti": "1.266",
    "perc": "2,26",
    "eletto": "",
    "perc_voti_liste": "",
    "cifra_el": "1.266",
    "perc_cifra_el": "2,26",
    "seggi": ""
  },
  {
    "assemblea": "Senato",
    "codice": "04160000000",
    "tipo": "colleggioUninominale",
    "tipo_riga": "XX",
    "cand_descr_riga": "",
    "img_lista": "",
    "descr_lista": "",
    "link_cand_lista": "",
    "voti": "",
    "perc": "",
    "eletto": "",
    "perc_voti_liste": "",
    "cifra_el": "",
    "perc_cifra_el": "",
    "seggi": ""
  },
  {
    "assemblea": "Senato",
    "codice": "04160000000",
    "tipo": "colleggioUninominale",
    "tipo_riga": "CA",
    "cand_descr_riga": "ANGELA D'ALESSANDRO",
    "img_lista": "",
    "descr_lista": "",
    "link_cand_lista": "",
    "voti": "570",
    "perc": "0,95",
    "eletto": "",
    "perc_voti_liste": "",
    "cifra_el": "",
    "perc_cifra_el": "",
    "seggi": ""
  },
  {
    "assemblea": "Senato",
    "codice": "04160000000",
    "tipo": "colleggioUninominale",
    "tipo_riga": "LI",
    "cand_descr_riga": "",
    "img_lista": "25-20180304000000-11277-0.png",
    "descr_lista": "IL POPOLO DELLA FAMIGLIA",
    "link_cand_lista": "",
    "voti": "527",
    "perc": "0,94",
    "eletto": "",
    "perc_voti_liste": "",
    "cifra_el": "527",
    "perc_cifra_el": "0,94",
    "seggi": ""
  },
  {
    "assemblea": "Senato",
    "codice": "04160000000",
    "tipo": "colleggioUninominale",
    "tipo_riga": "XX",
    "cand_descr_riga": "",
    "img_lista": "",
    "descr_lista": "",
    "link_cand_lista": "",
    "voti": "",
    "perc": "",
    "eletto": "",
    "perc_voti_liste": "",
    "cifra_el": "",
    "perc_cifra_el": "",
    "seggi": ""
  },
  {
    "assemblea": "Senato",
    "codice": "04160000000",
    "tipo": "colleggioUninominale",
    "tipo_riga": "CA",
    "cand_descr_riga": "ROBERTO BORDIN",
    "img_lista": "",
    "descr_lista": "",
    "link_cand_lista": "",
    "voti": "567",
    "perc": "0,95",
    "eletto": "",
    "perc_voti_liste": "",
    "cifra_el": "",
    "perc_cifra_el": "",
    "seggi": ""
  },
  {
    "assemblea": "Senato",
    "codice": "04160000000",
    "tipo": "colleggioUninominale",
    "tipo_riga": "LI",
    "cand_descr_riga": "",
    "img_lista": "25-20180304000000-11372-0.png",
    "descr_lista": "POTERE AL POPOLO!",
    "link_cand_lista": "",
    "voti": "534",
    "perc": "0,95",
    "eletto": "",
    "perc_voti_liste": "",
    "cifra_el": "534",
    "perc_cifra_el": "0,95",
    "seggi": ""
  },
  {
    "assemblea": "Senato",
    "codice": "04160000000",
    "tipo": "colleggioUninominale",
    "tipo_riga": "XX",
    "cand_descr_riga": "",
    "img_lista": "",
    "descr_lista": "",
    "link_cand_lista": "",
    "voti": "",
    "perc": "",
    "eletto": "",
    "perc_voti_liste": "",
    "cifra_el": "",
    "perc_cifra_el": "",
    "seggi": ""
  },
  {
    "assemblea": "Senato",
    "codice": "04160000000",
    "tipo": "colleggioUninominale",
    "tipo_riga": "CA",
    "cand_descr_riga": "ANGELA PALMISANO TRIPODI",
    "img_lista": "",
    "descr_lista": "",
    "link_cand_lista": "",
    "voti": "567",
    "perc": "0,95",
    "eletto": "",
    "perc_voti_liste": "",
    "cifra_el": "",
    "perc_cifra_el": "",
    "seggi": ""
  },
  {
    "assemblea": "Senato",
    "codice": "04160000000",
    "tipo": "colleggioUninominale",
    "tipo_riga": "LI",
    "cand_descr_riga": "",
    "img_lista": "25-20180304000000-11003-0.png",
    "descr_lista": "CASAPOUND ITALIA",
    "link_cand_lista": "",
    "voti": "533",
    "perc": "0,95",
    "eletto": "",
    "perc_voti_liste": "",
    "cifra_el": "533",
    "perc_cifra_el": "0,95",
    "seggi": ""
  },
  {
    "assemblea": "Senato",
    "codice": "04160000000",
    "tipo": "colleggioUninominale",
    "tipo_riga": "XX",
    "cand_descr_riga": "",
    "img_lista": "",
    "descr_lista": "",
    "link_cand_lista": "",
    "voti": "",
    "perc": "",
    "eletto": "",
    "perc_voti_liste": "",
    "cifra_el": "",
    "perc_cifra_el": "",
    "seggi": ""
  },
  {
    "assemblea": "Senato",
    "codice": "04160000000",
    "tipo": "colleggioUninominale",
    "tipo_riga": "TU",
    "cand_descr_riga": "Uninominale",
    "img_lista": "",
    "descr_lista": "",
    "link_cand_lista": "",
    "voti": "59.457",
    "perc": "100,00",
    "eletto": "",
    "perc_voti_liste": "",
    "cifra_el": "",
    "perc_cifra_el": "",
    "seggi": ""
  },
  {
    "assemblea": "Senato",
    "codice": "04160000000",
    "tipo": "colleggioUninominale",
    "tipo_riga": "TP",
    "cand_descr_riga": "Proporzionale",
    "img_lista": "",
    "descr_lista": "",
    "link_cand_lista": "",
    "voti": "55.868",
    "perc": "100,00",
    "eletto": "",
    "perc_voti_liste": "100,00",
    "cifra_el": "",
    "perc_cifra_el": "",
    "seggi": ""
  }
]
