[
  {
    "assemblea": "Senato",
    "codice": "12300000000",
    "tipo": "colleggioPlurinominale",
    "tipo_riga": "CU",
    "cand_descr_riga": "CANDIDATI UNINOMINALI",
    "img_lista": "",
    "descr_lista": "",
    "link_cand_lista": "",
    "voti": "417326",
    "perc": "38,50",
    "eletto": "",
    "perc_voti_liste": "",
    "cifra_el": "417326",
    "perc_cifra_el": "38,50",
    "seggi": "-"
  },
  {
    "assemblea": "Senato",
    "codice": "12300000000",
    "tipo": "colleggioPlurinominale",
    "tipo_riga": "LI",
    "cand_descr_riga": "",
    "img_lista": "25-20180304000000-1112-0.png",
    "descr_lista": "FORZA ITALIA",
    "link_cand_lista": null,
    "voti": "172190",
    "perc": "16,63",
    "eletto": "",
    "perc_voti_liste": "",
    "cifra_el": "172190",
    "perc_cifra_el": "16,63",
    "seggi": "-"
  },
  {
    "assemblea": "Senato",
    "codice": "12300000000",
    "tipo": "colleggioPlurinominale",
    "tipo_riga": "LI",
    "cand_descr_riga": "",
    "img_lista": "25-20180304000000-11367-0.png",
    "descr_lista": "LEGA",
    "link_cand_lista": null,
    "voti": "153614",
    "perc": "14,84",
    "eletto": "",
    "perc_voti_liste": "",
    "cifra_el": "153614",
    "perc_cifra_el": "14,84",
    "seggi": "-"
  },
  {
    "assemblea": "Senato",
    "codice": "12300000000",
    "tipo": "colleggioPlurinominale",
    "tipo_riga": "LI",
    "cand_descr_riga": "",
    "img_lista": "25-20180304000000-11434-0.png",
    "descr_lista": "FRATELLI D'ITALIA CON GIORGIA MELONI",
    "link_cand_lista": null,
    "voti": "68824",
    "perc": "6,64",
    "eletto": "",
    "perc_voti_liste": "",
    "cifra_el": "68824",
    "perc_cifra_el": "6,64",
    "seggi": "-"
  },
  {
    "assemblea": "Senato",
    "codice": "12300000000",
    "tipo": "colleggioPlurinominale",
    "tipo_riga": "LI",
    "cand_descr_riga": "",
    "img_lista": "25-20180304000000-11402-0.png",
    "descr_lista": "NOI CON L'ITALIA - UDC",
    "link_cand_lista": null,
    "voti": "9013",
    "perc": "0,87",
    "eletto": "",
    "perc_voti_liste": "",
    "cifra_el": "9013",
    "perc_cifra_el": "0,87",
    "seggi": "-"
  },
  {
    "assemblea": "Senato",
    "codice": "12300000000",
    "tipo": "colleggioPlurinominale",
    "tipo_riga": "XX",
    "cand_descr_riga": "",
    "img_lista": "",
    "descr_lista": "",
    "link_cand_lista": "",
    "voti": "",
    "perc": "",
    "eletto": "",
    "perc_voti_liste": "",
    "cifra_el": "",
    "perc_cifra_el": "",
    "seggi": ""
  },
  {
    "assemblea": "Senato",
    "codice": "12300000000",
    "tipo": "colleggioPlurinominale",
    "tipo_riga": "CU",
    "cand_descr_riga": "CANDIDATI UNINOMINALI",
    "img_lista": "",
    "descr_lista": "",
    "link_cand_lista": "",
    "voti": "393085",
    "perc": "36,26",
    "eletto": "",
    "perc_voti_liste": "",
    "cifra_el": "393085",
    "perc_cifra_el": "36,26",
    "seggi": "-"
  },
  {
    "assemblea": "Senato",
    "codice": "12300000000",
    "tipo": "colleggioPlurinominale",
    "tipo_riga": "LI",
    "cand_descr_riga": "",
    "img_lista": "25-20180304000000-11366-0.png",
    "descr_lista": "MOVIMENTO 5 STELLE",
    "link_cand_lista": null,
    "voti": "371467",
    "perc": "35,88",
    "eletto": "",
    "perc_voti_liste": "",
    "cifra_el": "371467",
    "perc_cifra_el": "35,88",
    "seggi": "-"
  },
  {
    "assemblea": "Senato",
    "codice": "12300000000",
    "tipo": "colleggioPlurinominale",
    "tipo_riga": "XX",
    "cand_descr_riga": "",
    "img_lista": "",
    "descr_lista": "",
    "link_cand_lista": "",
    "voti": "",
    "perc": "",
    "eletto": "",
    "perc_voti_liste": "",
    "cifra_el": "",
    "perc_cifra_el": "",
    "seggi": ""
  },
  {
    "assemblea": "Senato",
    "codice": "12300000000",
    "tipo": "colleggioPlurinominale",
    "tipo_riga": "CU",
    "cand_descr_riga": "CANDIDATI UNINOMINALI",
    "img_lista": "",
    "descr_lista": "",
    "link_cand_lista": "",
    "voti": "194293",
    "perc": "17,92",
    "eletto": "",
    "perc_voti_liste": "",
    "cifra_el": "194293",
    "perc_cifra_el": "17,92",
    "seggi": "-"
  },
  {
    "assemblea": "Senato",
    "codice": "12300000000",
    "tipo": "colleggioPlurinominale",
    "tipo_riga": "LI",
    "cand_descr_riga": "",
    "img_lista": "25-20180304000000-3456-0.png",
    "descr_lista": "PARTITO DEMOCRATICO",
    "link_cand_lista": null,
    "voti": "159500",
    "perc": "15,40",
    "eletto": "",
    "perc_voti_liste": "",
    "cifra_el": "159500",
    "perc_cifra_el": "15,40",
    "seggi": "-"
  },
  {
    "assemblea": "Senato",
    "codice": "12300000000",
    "tipo": "colleggioPlurinominale",
    "tipo_riga": "LI",
    "cand_descr_riga": "",
    "img_lista": "25-20180304000000-11403-0.png",
    "descr_lista": "+EUROPA",
    "link_cand_lista": null,
    "voti": "16411",
    "perc": "1,58",
    "eletto": "",
    "perc_voti_liste": "",
    "cifra_el": "16411",
    "perc_cifra_el": "1,58",
    "seggi": "-"
  },
  {
    "assemblea": "Senato",
    "codice": "12300000000",
    "tipo": "colleggioPlurinominale",
    "tipo_riga": "LI",
    "cand_descr_riga": "",
    "img_lista": "25-20180304000000-11373-0.png",
    "descr_lista": "ITALIA EUROPA INSIEME",
    "link_cand_lista": null,
    "voti": "5704",
    "perc": "0,55",
    "eletto": "",
    "perc_voti_liste": "",
    "cifra_el": "5704",
    "perc_cifra_el": "0,55",
    "seggi": "-"
  },
  {
    "assemblea": "Senato",
    "codice": "12300000000",
    "tipo": "colleggioPlurinominale",
    "tipo_riga": "LI",
    "cand_descr_riga": "",
    "img_lista": "25-20180304000000-11412-0.png",
    "descr_lista": "CIVICA POPOLARE LORENZIN",
    "link_cand_lista": null,
    "voti": "4028",
    "perc": "0,38",
    "eletto": "",
    "perc_voti_liste": "",
    "cifra_el": "4028",
    "perc_cifra_el": "0,38",
    "seggi": "-"
  },
  {
    "assemblea": "Senato",
    "codice": "12300000000",
    "tipo": "colleggioPlurinominale",
    "tipo_riga": "XX",
    "cand_descr_riga": "",
    "img_lista": "",
    "descr_lista": "",
    "link_cand_lista": "",
    "voti": "",
    "perc": "",
    "eletto": "",
    "perc_voti_liste": "",
    "cifra_el": "",
    "perc_cifra_el": "",
    "seggi": ""
  },
  {
    "assemblea": "Senato",
    "codice": "12300000000",
    "tipo": "colleggioPlurinominale",
    "tipo_riga": "CU",
    "cand_descr_riga": "CANDIDATI UNINOMINALI",
    "img_lista": "",
    "descr_lista": "",
    "link_cand_lista": "",
    "voti": "31261",
    "perc": "2,88",
    "eletto": "",
    "perc_voti_liste": "",
    "cifra_el": "31261",
    "perc_cifra_el": "2,88",
    "seggi": "-"
  },
  {
    "assemblea": "Senato",
    "codice": "12300000000",
    "tipo": "colleggioPlurinominale",
    "tipo_riga": "LI",
    "cand_descr_riga": "",
    "img_lista": "25-20180304000000-11393-0.png",
    "descr_lista": "LIBERI E UGUALI",
    "link_cand_lista": null,
    "voti": "29260",
    "perc": "2,82",
    "eletto": "",
    "perc_voti_liste": "",
    "cifra_el": "29260",
    "perc_cifra_el": "2,82",
    "seggi": "-"
  },
  {
    "assemblea": "Senato",
    "codice": "12300000000",
    "tipo": "colleggioPlurinominale",
    "tipo_riga": "XX",
    "cand_descr_riga": "",
    "img_lista": "",
    "descr_lista": "",
    "link_cand_lista": "",
    "voti": "",
    "perc": "",
    "eletto": "",
    "perc_voti_liste": "",
    "cifra_el": "",
    "perc_cifra_el": "",
    "seggi": ""
  },
  {
    "assemblea": "Senato",
    "codice": "12300000000",
    "tipo": "colleggioPlurinominale",
    "tipo_riga": "CU",
    "cand_descr_riga": "CANDIDATI UNINOMINALI",
    "img_lista": "",
    "descr_lista": "",
    "link_cand_lista": "",
    "voti": "15771",
    "perc": "1,45",
    "eletto": "",
    "perc_voti_liste": "",
    "cifra_el": "15771",
    "perc_cifra_el": "1,45",
    "seggi": "-"
  },
  {
    "assemblea": "Senato",
    "codice": "12300000000",
    "tipo": "colleggioPlurinominale",
    "tipo_riga": "LI",
    "cand_descr_riga": "",
    "img_lista": "25-20180304000000-11003-0.png",
    "descr_lista": "CASAPOUND ITALIA",
    "link_cand_lista": null,
    "voti": "14921",
    "perc": "1,44",
    "eletto": "",
    "perc_voti_liste": "",
    "cifra_el": "14921",
    "perc_cifra_el": "1,44",
    "seggi": "-"
  },
  {
    "assemblea": "Senato",
    "codice": "12300000000",
    "tipo": "colleggioPlurinominale",
    "tipo_riga": "XX",
    "cand_descr_riga": "",
    "img_lista": "",
    "descr_lista": "",
    "link_cand_lista": "",
    "voti": "",
    "perc": "",
    "eletto": "",
    "perc_voti_liste": "",
    "cifra_el": "",
    "perc_cifra_el": "",
    "seggi": ""
  },
  {
    "assemblea": "Senato",
    "codice": "12300000000",
    "tipo": "colleggioPlurinominale",
    "tipo_riga": "CU",
    "cand_descr_riga": "CANDIDATI UNINOMINALI",
    "img_lista": "",
    "descr_lista": "",
    "link_cand_lista": "",
    "voti": "11175",
    "perc": "1,03",
    "eletto": "",
    "perc_voti_liste": "",
    "cifra_el": "11175",
    "perc_cifra_el": "1,03",
    "seggi": "-"
  },
  {
    "assemblea": "Senato",
    "codice": "12300000000",
    "tipo": "colleggioPlurinominale",
    "tipo_riga": "LI",
    "cand_descr_riga": "",
    "img_lista": "25-20180304000000-11372-0.png",
    "descr_lista": "POTERE AL POPOLO!",
    "link_cand_lista": null,
    "voti": "10487",
    "perc": "1,01",
    "eletto": "",
    "perc_voti_liste": "",
    "cifra_el": "10487",
    "perc_cifra_el": "1,01",
    "seggi": "-"
  },
  {
    "assemblea": "Senato",
    "codice": "12300000000",
    "tipo": "colleggioPlurinominale",
    "tipo_riga": "XX",
    "cand_descr_riga": "",
    "img_lista": "",
    "descr_lista": "",
    "link_cand_lista": "",
    "voti": "",
    "perc": "",
    "eletto": "",
    "perc_voti_liste": "",
    "cifra_el": "",
    "perc_cifra_el": "",
    "seggi": ""
  },
  {
    "assemblea": "Senato",
    "codice": "12300000000",
    "tipo": "colleggioPlurinominale",
    "tipo_riga": "CU",
    "cand_descr_riga": "CANDIDATI UNINOMINALI",
    "img_lista": "",
    "descr_lista": "",
    "link_cand_lista": "",
    "voti": "5639",
    "perc": "0,52",
    "eletto": "",
    "perc_voti_liste": "",
    "cifra_el": "5639",
    "perc_cifra_el": "0,52",
    "seggi": "-"
  },
  {
    "assemblea": "Senato",
    "codice": "12300000000",
    "tipo": "colleggioPlurinominale",
    "tipo_riga": "LI",
    "cand_descr_riga": "",
    "img_lista": "25-20180304000000-11023-0.png",
    "descr_lista": "PARTITO COMUNISTA",
    "link_cand_lista": null,
    "voti": "5267",
    "perc": "0,50",
    "eletto": "",
    "perc_voti_liste": "",
    "cifra_el": "5267",
    "perc_cifra_el": "0,50",
    "seggi": "-"
  },
  {
    "assemblea": "Senato",
    "codice": "12300000000",
    "tipo": "colleggioPlurinominale",
    "tipo_riga": "XX",
    "cand_descr_riga": "",
    "img_lista": "",
    "descr_lista": "",
    "link_cand_lista": "",
    "voti": "",
    "perc": "",
    "eletto": "",
    "perc_voti_liste": "",
    "cifra_el": "",
    "perc_cifra_el": "",
    "seggi": ""
  },
  {
    "assemblea": "Senato",
    "codice": "12300000000",
    "tipo": "colleggioPlurinominale",
    "tipo_riga": "CU",
    "cand_descr_riga": "CANDIDATI UNINOMINALI",
    "img_lista": "",
    "descr_lista": "",
    "link_cand_lista": "",
    "voti": "5251",
    "perc": "0,48",
    "eletto": "",
    "perc_voti_liste": "",
    "cifra_el": "5251",
    "perc_cifra_el": "0,48",
    "seggi": "-"
  },
  {
    "assemblea": "Senato",
    "codice": "12300000000",
    "tipo": "colleggioPlurinominale",
    "tipo_riga": "LI",
    "cand_descr_riga": "",
    "img_lista": "25-20180304000000-11388-0.png",
    "descr_lista": "ITALIA AGLI ITALIANI",
    "link_cand_lista": null,
    "voti": "4987",
    "perc": "0,48",
    "eletto": "",
    "perc_voti_liste": "",
    "cifra_el": "4987",
    "perc_cifra_el": "0,48",
    "seggi": "-"
  },
  {
    "assemblea": "Senato",
    "codice": "12300000000",
    "tipo": "colleggioPlurinominale",
    "tipo_riga": "XX",
    "cand_descr_riga": "",
    "img_lista": "",
    "descr_lista": "",
    "link_cand_lista": "",
    "voti": "",
    "perc": "",
    "eletto": "",
    "perc_voti_liste": "",
    "cifra_el": "",
    "perc_cifra_el": "",
    "seggi": ""
  },
  {
    "assemblea": "Senato",
    "codice": "12300000000",
    "tipo": "colleggioPlurinominale",
    "tipo_riga": "CU",
    "cand_descr_riga": "CANDIDATI UNINOMINALI",
    "img_lista": "",
    "descr_lista": "",
    "link_cand_lista": "",
    "voti": "4914",
    "perc": "0,45",
    "eletto": "",
    "perc_voti_liste": "",
    "cifra_el": "4914",
    "perc_cifra_el": "0,45",
    "seggi": "-"
  },
  {
    "assemblea": "Senato",
    "codice": "12300000000",
    "tipo": "colleggioPlurinominale",
    "tipo_riga": "LI",
    "cand_descr_riga": "",
    "img_lista": "25-20180304000000-11277-0.png",
    "descr_lista": "IL POPOLO DELLA FAMIGLIA",
    "link_cand_lista": null,
    "voti": "4628",
    "perc": "0,44",
    "eletto": "",
    "perc_voti_liste": "",
    "cifra_el": "4628",
    "perc_cifra_el": "0,44",
    "seggi": "-"
  },
  {
    "assemblea": "Senato",
    "codice": "12300000000",
    "tipo": "colleggioPlurinominale",
    "tipo_riga": "XX",
    "cand_descr_riga": "",
    "img_lista": "",
    "descr_lista": "",
    "link_cand_lista": "",
    "voti": "",
    "perc": "",
    "eletto": "",
    "perc_voti_liste": "",
    "cifra_el": "",
    "perc_cifra_el": "",
    "seggi": ""
  },
  {
    "assemblea": "Senato",
    "codice": "12300000000",
    "tipo": "colleggioPlurinominale",
    "tipo_riga": "CU",
    "cand_descr_riga": "CANDIDATI UNINOMINALI",
    "img_lista": "",
    "descr_lista": "",
    "link_cand_lista": "",
    "voti": "2063",
    "perc": "0,19",
    "eletto": "",
    "perc_voti_liste": "",
    "cifra_el": "2063",
    "perc_cifra_el": "0,19",
    "seggi": "-"
  },
  {
    "assemblea": "Senato",
    "codice": "12300000000",
    "tipo": "colleggioPlurinominale",
    "tipo_riga": "LI",
    "cand_descr_riga": "",
    "img_lista": "25-20180304000000-3142-0.png",
    "descr_lista": "DEMOCRAZIA CRISTIANA",
    "link_cand_lista": null,
    "voti": "1944",
    "perc": "0,18",
    "eletto": "",
    "perc_voti_liste": "",
    "cifra_el": "1944",
    "perc_cifra_el": "0,18",
    "seggi": "-"
  },
  {
    "assemblea": "Senato",
    "codice": "12300000000",
    "tipo": "colleggioPlurinominale",
    "tipo_riga": "XX",
    "cand_descr_riga": "",
    "img_lista": "",
    "descr_lista": "",
    "link_cand_lista": "",
    "voti": "",
    "perc": "",
    "eletto": "",
    "perc_voti_liste": "",
    "cifra_el": "",
    "perc_cifra_el": "",
    "seggi": ""
  },
  {
    "assemblea": "Senato",
    "codice": "12300000000",
    "tipo": "colleggioPlurinominale",
    "tipo_riga": "CU",
    "cand_descr_riga": "CANDIDATI UNINOMINALI",
    "img_lista": "",
    "descr_lista": "",
    "link_cand_lista": "",
    "voti": "1204",
    "perc": "0,11",
    "eletto": "",
    "perc_voti_liste": "",
    "cifra_el": "1204",
    "perc_cifra_el": "0,11",
    "seggi": "-"
  },
  {
    "assemblea": "Senato",
    "codice": "12300000000",
    "tipo": "colleggioPlurinominale",
    "tipo_riga": "LI",
    "cand_descr_riga": "",
    "img_lista": "25-20180304000000-11377-0.png",
    "descr_lista": "PER UNA SINISTRA RIVOLUZIONARIA",
    "link_cand_lista": null,
    "voti": "1121",
    "perc": "0,10",
    "eletto": "",
    "perc_voti_liste": "",
    "cifra_el": "1121",
    "perc_cifra_el": "0,10",
    "seggi": "-"
  },
  {
    "assemblea": "Senato",
    "codice": "12300000000",
    "tipo": "colleggioPlurinominale",
    "tipo_riga": "XX",
    "cand_descr_riga": "",
    "img_lista": "",
    "descr_lista": "",
    "link_cand_lista": "",
    "voti": "",
    "perc": "",
    "eletto": "",
    "perc_voti_liste": "",
    "cifra_el": "",
    "perc_cifra_el": "",
    "seggi": ""
  },
  {
    "assemblea": "Senato",
    "codice": "12300000000",
    "tipo": "colleggioPlurinominale",
    "tipo_riga": "CU",
    "cand_descr_riga": "CANDIDATI UNINOMINALI",
    "img_lista": "",
    "descr_lista": "",
    "link_cand_lista": "",
    "voti": "1118",
    "perc": "0,10",
    "eletto": "",
    "perc_voti_liste": "",
    "cifra_el": "1118",
    "perc_cifra_el": "0,10",
    "seggi": "-"
  },
  {
    "assemblea": "Senato",
    "codice": "12300000000",
    "tipo": "colleggioPlurinominale",
    "tipo_riga": "LI",
    "cand_descr_riga": "",
    "img_lista": "25-20180304000000-11418-0.png",
    "descr_lista": "PARTITO REPUBBLICANO ITALIANO - ALA",
    "link_cand_lista": null,
    "voti": "1054",
    "perc": "0,10",
    "eletto": "",
    "perc_voti_liste": "",
    "cifra_el": "1054",
    "perc_cifra_el": "0,10",
    "seggi": "-"
  },
  {
    "assemblea": "Senato",
    "codice": "12300000000",
    "tipo": "colleggioPlurinominale",
    "tipo_riga": "XX",
    "cand_descr_riga": "",
    "img_lista": "",
    "descr_lista": "",
    "link_cand_lista": "",
    "voti": "",
    "perc": "",
    "eletto": "",
    "perc_voti_liste": "",
    "cifra_el": "",
    "perc_cifra_el": "",
    "seggi": ""
  },
  {
    "assemblea": "Senato",
    "codice": "12300000000",
    "tipo": "colleggioPlurinominale",
    "tipo_riga": "CU",
    "cand_descr_riga": "CANDIDATI UNINOMINALI",
    "img_lista": "",
    "descr_lista": "",
    "link_cand_lista": "",
    "voti": "753",
    "perc": "0,06",
    "eletto": "",
    "perc_voti_liste": "",
    "cifra_el": "753",
    "perc_cifra_el": "0,06",
    "seggi": "-"
  },
  {
    "assemblea": "Senato",
    "codice": "12300000000",
    "tipo": "colleggioPlurinominale",
    "tipo_riga": "LI",
    "cand_descr_riga": "",
    "img_lista": "25-20180304000000-11400-0.png",
    "descr_lista": "LISTA DEL POPOLO PER LA COSTITUZIONE",
    "link_cand_lista": null,
    "voti": "695",
    "perc": "0,06",
    "eletto": "",
    "perc_voti_liste": "",
    "cifra_el": "695",
    "perc_cifra_el": "0,06",
    "seggi": "-"
  },
  {
    "assemblea": "Senato",
    "codice": "12300000000",
    "tipo": "colleggioPlurinominale",
    "tipo_riga": "XX",
    "cand_descr_riga": "",
    "img_lista": "",
    "descr_lista": "",
    "link_cand_lista": "",
    "voti": "",
    "perc": "",
    "eletto": "",
    "perc_voti_liste": "",
    "cifra_el": "",
    "perc_cifra_el": "",
    "seggi": ""
  },
  {
    "assemblea": "Senato",
    "codice": "12300000000",
    "tipo": "colleggioPlurinominale",
    "tipo_riga": "TU",
    "cand_descr_riga": "Uninominale",
    "img_lista": "",
    "descr_lista": "",
    "link_cand_lista": "",
    "voti": "1083853",
    "perc": "100,00",
    "eletto": "",
    "perc_voti_liste": "",
    "cifra_el": "1083853",
    "perc_cifra_el": "100,00",
    "seggi": "0"
  },
  {
    "assemblea": "Senato",
    "codice": "12300000000",
    "tipo": "colleggioPlurinominale",
    "tipo_riga": "TP",
    "cand_descr_riga": "Proporzionale",
    "img_lista": "",
    "descr_lista": "",
    "link_cand_lista": "",
    "voti": "1035115",
    "perc": "100,00",
    "eletto": "",
    "perc_voti_liste": "",
    "cifra_el": "1035115",
    "perc_cifra_el": "100,00",
    "seggi": "0"
  }
]
