{ 
"status": "ESERCIZIO",
"elettori": "198.945",
"votanti": "-",
"perc_votanti": "-",
"aggiornamento": "Dato aggiornato al 05/03/2018 - 10:25",
"sezioni_perv": "264",
"sezioni": "280",
"coll_uni_perv": "",
"coll_uni": "",
"sezioni_coll_uni_perv": "-",
"sk_bianche": "-",
"sk_nulle": "-",
"sk_contestate": "-",		
"livello": "U",
"flag_eletto": "",  
"note": [
	{"testo": ""}
	],
"righe": [
	{"tipo_riga": "CA", "cand_descr_riga": "MICHELE GUBITOSA", "img_lista": "", "descr_lista": "", "link_cand_lista": "", "voti": "57.713", "perc": "44,03", "eletto": "", "perc_voti_liste": "", "cifra_el": "", "perc_cifra_el": "", "seggi": "", "voti_cand": "2.768"},
     {"tipo_riga": "LI", "cand_descr_riga": "", "img_lista": "24-20180304000000-11366-0.png", "descr_lista": "MOVIMENTO 5 STELLE", "link_cand_lista": "", "voti": "54.945", "perc": "43,95", "eletto": "", "perc_voti_liste": "", "cifra_el": "54.945", "perc_cifra_el": "43,95", "seggi": "", "una_lista": "S"},
	{"tipo_riga": "XX", "cand_descr_riga": "", "img_lista": "", "descr_lista": "", "link_cand_lista": "", "voti": "", "perc": "", "eletto": "", "perc_voti_liste": "", "cifra_el": "", "perc_cifra_el": "", "seggi": ""},
	{"tipo_riga": "CA", "cand_descr_riga": "PIETRO FOGLIA", "img_lista": "", "descr_lista": "", "link_cand_lista": "", "voti": "36.714", "perc": "28,01", "eletto": "", "perc_voti_liste": "", "cifra_el": "", "perc_cifra_el": "", "seggi": "", "voti_cand": "1.080"},
     {"tipo_riga": "LI", "cand_descr_riga": "", "img_lista": "24-20180304000000-1112-0.png", "descr_lista": "FORZA ITALIA", "link_cand_lista": "", "voti": "21.473", "perc": "17,17", "eletto": "", "perc_voti_liste": "", "cifra_el": "21.473", "perc_cifra_el": "17,17", "seggi": "", "una_lista": "N"},
     {"tipo_riga": "LI", "cand_descr_riga": "", "img_lista": "24-20180304000000-11367-0.png", "descr_lista": "LEGA", "link_cand_lista": "", "voti": "6.666", "perc": "5,33", "eletto": "", "perc_voti_liste": "", "cifra_el": "6.666", "perc_cifra_el": "5,33", "seggi": "", "una_lista": "N"},
     {"tipo_riga": "LI", "cand_descr_riga": "", "img_lista": "24-20180304000000-11434-0.png", "descr_lista": "FRATELLI D'ITALIA CON GIORGIA MELONI", "link_cand_lista": "", "voti": "5.803", "perc": "4,64", "eletto": "", "perc_voti_liste": "", "cifra_el": "5.803", "perc_cifra_el": "4,64", "seggi": "", "una_lista": "N"},
     {"tipo_riga": "LI", "cand_descr_riga": "", "img_lista": "24-20180304000000-11402-0.png", "descr_lista": "NOI CON L'ITALIA - UDC", "link_cand_lista": "", "voti": "1.692", "perc": "1,35", "eletto": "", "perc_voti_liste": "", "cifra_el": "1.692", "perc_cifra_el": "1,35", "seggi": "", "una_lista": "N"},
	{"tipo_riga": "XX", "cand_descr_riga": "", "img_lista": "", "descr_lista": "", "link_cand_lista": "", "voti": "", "perc": "", "eletto": "", "perc_voti_liste": "", "cifra_el": "", "perc_cifra_el": "", "seggi": ""},
	{"tipo_riga": "CA", "cand_descr_riga": "ANGELO ANTONIO D'AGOSTINO", "img_lista": "", "descr_lista": "", "link_cand_lista": "", "voti": "27.464", "perc": "20,95", "eletto": "", "perc_voti_liste": "", "cifra_el": "", "perc_cifra_el": "", "seggi": "", "voti_cand": "1.602"},
     {"tipo_riga": "LI", "cand_descr_riga": "", "img_lista": "24-20180304000000-3456-0.png", "descr_lista": "PARTITO DEMOCRATICO", "link_cand_lista": "", "voti": "19.050", "perc": "15,23", "eletto": "", "perc_voti_liste": "", "cifra_el": "19.050", "perc_cifra_el": "15,23", "seggi": "", "una_lista": "N"},
     {"tipo_riga": "LI", "cand_descr_riga": "", "img_lista": "24-20180304000000-11373-0.png", "descr_lista": "ITALIA EUROPA INSIEME", "link_cand_lista": "", "voti": "2.754", "perc": "2,20", "eletto": "", "perc_voti_liste": "", "cifra_el": "2.754", "perc_cifra_el": "2,20", "seggi": "", "una_lista": "N"},
     {"tipo_riga": "LI", "cand_descr_riga": "", "img_lista": "24-20180304000000-11412-0.png", "descr_lista": "CIVICA POPOLARE LORENZIN", "link_cand_lista": "", "voti": "2.096", "perc": "1,67", "eletto": "", "perc_voti_liste": "", "cifra_el": "2.096", "perc_cifra_el": "1,67", "seggi": "", "una_lista": "N"},
     {"tipo_riga": "LI", "cand_descr_riga": "", "img_lista": "24-20180304000000-11403-0.png", "descr_lista": "+EUROPA", "link_cand_lista": "", "voti": "1.962", "perc": "1,56", "eletto": "", "perc_voti_liste": "", "cifra_el": "1.962", "perc_cifra_el": "1,56", "seggi": "", "una_lista": "N"},
	{"tipo_riga": "XX", "cand_descr_riga": "", "img_lista": "", "descr_lista": "", "link_cand_lista": "", "voti": "", "perc": "", "eletto": "", "perc_voti_liste": "", "cifra_el": "", "perc_cifra_el": "", "seggi": ""},
	{"tipo_riga": "CA", "cand_descr_riga": "ANNAMARIA PASCALE", "img_lista": "", "descr_lista": "", "link_cand_lista": "", "voti": "4.384", "perc": "3,34", "eletto": "", "perc_voti_liste": "", "cifra_el": "", "perc_cifra_el": "", "seggi": "", "voti_cand": "347"},
     {"tipo_riga": "LI", "cand_descr_riga": "", "img_lista": "24-20180304000000-11393-0.png", "descr_lista": "LIBERI E UGUALI", "link_cand_lista": "", "voti": "4.037", "perc": "3,22", "eletto": "", "perc_voti_liste": "", "cifra_el": "4.037", "perc_cifra_el": "3,22", "seggi": "", "una_lista": "S"},
	{"tipo_riga": "XX", "cand_descr_riga": "", "img_lista": "", "descr_lista": "", "link_cand_lista": "", "voti": "", "perc": "", "eletto": "", "perc_voti_liste": "", "cifra_el": "", "perc_cifra_el": "", "seggi": ""},
	{"tipo_riga": "CA", "cand_descr_riga": "ANTONIO DELLA PIA DETTO TONY", "img_lista": "", "descr_lista": "", "link_cand_lista": "", "voti": "1.926", "perc": "1,46", "eletto": "", "perc_voti_liste": "", "cifra_el": "", "perc_cifra_el": "", "seggi": "", "voti_cand": "104"},
     {"tipo_riga": "LI", "cand_descr_riga": "", "img_lista": "24-20180304000000-11372-0.png", "descr_lista": "POTERE AL POPOLO!", "link_cand_lista": "", "voti": "1.822", "perc": "1,45", "eletto": "", "perc_voti_liste": "", "cifra_el": "1.822", "perc_cifra_el": "1,45", "seggi": "", "una_lista": "S"},
	{"tipo_riga": "XX", "cand_descr_riga": "", "img_lista": "", "descr_lista": "", "link_cand_lista": "", "voti": "", "perc": "", "eletto": "", "perc_voti_liste": "", "cifra_el": "", "perc_cifra_el": "", "seggi": ""},
	{"tipo_riga": "CA", "cand_descr_riga": "GIULIANO BELLO", "img_lista": "", "descr_lista": "", "link_cand_lista": "", "voti": "811", "perc": "0,61", "eletto": "", "perc_voti_liste": "", "cifra_el": "", "perc_cifra_el": "", "seggi": "", "voti_cand": "38"},
     {"tipo_riga": "LI", "cand_descr_riga": "", "img_lista": "24-20180304000000-11003-0.png", "descr_lista": "CASAPOUND ITALIA", "link_cand_lista": "", "voti": "773", "perc": "0,61", "eletto": "", "perc_voti_liste": "", "cifra_el": "773", "perc_cifra_el": "0,61", "seggi": "", "una_lista": "S"},
	{"tipo_riga": "XX", "cand_descr_riga": "", "img_lista": "", "descr_lista": "", "link_cand_lista": "", "voti": "", "perc": "", "eletto": "", "perc_voti_liste": "", "cifra_el": "", "perc_cifra_el": "", "seggi": ""},
	{"tipo_riga": "CA", "cand_descr_riga": "MICHELE ANTONIO GILIBERTI", "img_lista": "", "descr_lista": "", "link_cand_lista": "", "voti": "692", "perc": "0,52", "eletto": "", "perc_voti_liste": "", "cifra_el": "", "perc_cifra_el": "", "seggi": "", "voti_cand": "39"},
     {"tipo_riga": "LI", "cand_descr_riga": "", "img_lista": "24-20180304000000-11388-0.png", "descr_lista": "ITALIA AGLI ITALIANI", "link_cand_lista": "", "voti": "653", "perc": "0,52", "eletto": "", "perc_voti_liste": "", "cifra_el": "653", "perc_cifra_el": "0,52", "seggi": "", "una_lista": "S"},
	{"tipo_riga": "XX", "cand_descr_riga": "", "img_lista": "", "descr_lista": "", "link_cand_lista": "", "voti": "", "perc": "", "eletto": "", "perc_voti_liste": "", "cifra_el": "", "perc_cifra_el": "", "seggi": ""},
	{"tipo_riga": "CA", "cand_descr_riga": "CATIA LIDIA CARBONELLI", "img_lista": "", "descr_lista": "", "link_cand_lista": "", "voti": "496", "perc": "0,37", "eletto": "", "perc_voti_liste": "", "cifra_el": "", "perc_cifra_el": "", "seggi": "", "voti_cand": "31"},
     {"tipo_riga": "LI", "cand_descr_riga": "", "img_lista": "24-20180304000000-11023-0.png", "descr_lista": "PARTITO COMUNISTA", "link_cand_lista": "", "voti": "465", "perc": "0,37", "eletto": "", "perc_voti_liste": "", "cifra_el": "465", "perc_cifra_el": "0,37", "seggi": "", "una_lista": "S"},
	{"tipo_riga": "XX", "cand_descr_riga": "", "img_lista": "", "descr_lista": "", "link_cand_lista": "", "voti": "", "perc": "", "eletto": "", "perc_voti_liste": "", "cifra_el": "", "perc_cifra_el": "", "seggi": ""},
	{"tipo_riga": "CA", "cand_descr_riga": "GIANCARLO MARCOCCI", "img_lista": "", "descr_lista": "", "link_cand_lista": "", "voti": "341", "perc": "0,26", "eletto": "", "perc_voti_liste": "", "cifra_el": "", "perc_cifra_el": "", "seggi": "", "voti_cand": "17"},
     {"tipo_riga": "LI", "cand_descr_riga": "", "img_lista": "24-20180304000000-11277-0.png", "descr_lista": "IL POPOLO DELLA FAMIGLIA", "link_cand_lista": "", "voti": "324", "perc": "0,25", "eletto": "", "perc_voti_liste": "", "cifra_el": "324", "perc_cifra_el": "0,25", "seggi": "", "una_lista": "S"},
	{"tipo_riga": "XX", "cand_descr_riga": "", "img_lista": "", "descr_lista": "", "link_cand_lista": "", "voti": "", "perc": "", "eletto": "", "perc_voti_liste": "", "cifra_el": "", "perc_cifra_el": "", "seggi": ""},
	{"tipo_riga": "CA", "cand_descr_riga": "GENNARO BLASI", "img_lista": "", "descr_lista": "", "link_cand_lista": "", "voti": "289", "perc": "0,22", "eletto": "", "perc_voti_liste": "", "cifra_el": "", "perc_cifra_el": "", "seggi": "", "voti_cand": "13"},
     {"tipo_riga": "LI", "cand_descr_riga": "", "img_lista": "24-20180304000000-11381-0.png", "descr_lista": "PARTITO VALORE UMANO", "link_cand_lista": "", "voti": "276", "perc": "0,22", "eletto": "", "perc_voti_liste": "", "cifra_el": "276", "perc_cifra_el": "0,22", "seggi": "", "una_lista": "S"},
	{"tipo_riga": "XX", "cand_descr_riga": "", "img_lista": "", "descr_lista": "", "link_cand_lista": "", "voti": "", "perc": "", "eletto": "", "perc_voti_liste": "", "cifra_el": "", "perc_cifra_el": "", "seggi": ""},
	{"tipo_riga": "CA", "cand_descr_riga": "GIAMMARCO COVIELLO", "img_lista": "", "descr_lista": "", "link_cand_lista": "", "voti": "135", "perc": "0,10", "eletto": "", "perc_voti_liste": "", "cifra_el": "", "perc_cifra_el": "", "seggi": "", "voti_cand": "12"},
     {"tipo_riga": "LI", "cand_descr_riga": "", "img_lista": "24-20180304000000-11368-0.png", "descr_lista": "10 VOLTE MEGLIO", "link_cand_lista": "", "voti": "123", "perc": "0,09", "eletto": "", "perc_voti_liste": "", "cifra_el": "123", "perc_cifra_el": "0,09", "seggi": "", "una_lista": "S"},
	{"tipo_riga": "XX", "cand_descr_riga": "", "img_lista": "", "descr_lista": "", "link_cand_lista": "", "voti": "", "perc": "", "eletto": "", "perc_voti_liste": "", "cifra_el": "", "perc_cifra_el": "", "seggi": ""},
	{"tipo_riga": "CA", "cand_descr_riga": "GIULIA GODANO", "img_lista": "", "descr_lista": "", "link_cand_lista": "", "voti": "101", "perc": "0,07", "eletto": "", "perc_voti_liste": "", "cifra_el": "", "perc_cifra_el": "", "seggi": "", "voti_cand": "8"},
     {"tipo_riga": "LI", "cand_descr_riga": "", "img_lista": "24-20180304000000-11400-0.png", "descr_lista": "LISTA DEL POPOLO PER LA COSTITUZIONE", "link_cand_lista": "", "voti": "93", "perc": "0,07", "eletto": "", "perc_voti_liste": "", "cifra_el": "93", "perc_cifra_el": "0,07", "seggi": "", "una_lista": "S"},
	{"tipo_riga": "XX", "cand_descr_riga": "", "img_lista": "", "descr_lista": "", "link_cand_lista": "", "voti": "", "perc": "", "eletto": "", "perc_voti_liste": "", "cifra_el": "", "perc_cifra_el": "", "seggi": ""},
	{"tipo_riga": "TU", "cand_descr_riga": "Uninominale", "img_lista": "", "descr_lista": "", "link_cand_lista": "", "voti": "131.066", "perc": "100,00", "eletto": "", "perc_voti_liste": "", "cifra_el": "", "perc_cifra_el": "", "seggi": ""},
	{"tipo_riga": "TP", "cand_descr_riga": "Proporzionale", "img_lista": "", "descr_lista": "", "link_cand_lista": "", "voti": "125.007", "perc": "100,00", "eletto": "", "perc_voti_liste": "100,00", "cifra_el": "", "perc_cifra_el": "", "seggi": ""}		
	]				               
 }	
	